{
  "data": {
    "article": {},
    "attachments": {},
    "author_id": "1839263401845075974",
    "conversation_id": "1985364959094620552",
    "created_at": "2025-11-04T17:35:28.000Z",
    "edit_controls": {
      "editable_until": "2025-11-04T18:35:28.000Z",
      "edits_remaining": 5,
      "is_edit_eligible": false
    },
    "edit_history_tweet_ids": [
      "1985762835922895153"
    ],
    "entities": {
      "mentions": [
        {
          "end": 12,
          "id": "1870313420807163904",
          "start": 0,
          "username": "IzayoiMarin"
        }
      ]
    },
    "geo": {},
    "id": "1985762835922895153",
    "in_reply_to_user_id": "1870313420807163904",
    "lang": "zh",
    "note_tweet": {
      "entities": {}
    },
    "possibly_sensitive": false,
    "public_metrics": {
      "bookmark_count": 0,
      "impression_count": 0,
      "like_count": 0,
      "quote_count": 0,
      "reply_count": 0,
      "retweet_count": 0
    },
    "referenced_tweets": [
      {
        "id": "1985364959094620552",
        "type": "replied_to"
      }
    ],
    "reply_settings": "everyone",
    "text": "@IzayoiMarin 3,4反人类罪"
  },
  "includes": {
    "tweets": [
      {
        "article": {},
        "attachments": {},
        "author_id": "1839263401845075974",
        "conversation_id": "1985364959094620552",
        "created_at": "2025-11-04T17:35:28.000Z",
        "edit_controls": {
          "editable_until": "2025-11-04T18:35:28.000Z",
          "edits_remaining": 5,
          "is_edit_eligible": false
        },
        "edit_history_tweet_ids": [
          "1985762835922895153"
        ],
        "entities": {
          "mentions": [
            {
              "end": 12,
              "id": "1870313420807163904",
              "start": 0,
              "username": "IzayoiMarin"
            }
          ]
        },
        "geo": {},
        "id": "1985762835922895153",
        "in_reply_to_user_id": "1870313420807163904",
        "lang": "zh",
        "note_tweet": {
          "entities": {}
        },
        "possibly_sensitive": false,
        "public_metrics": {
          "bookmark_count": 0,
          "impression_count": 0,
          "like_count": 0,
          "quote_count": 0,
          "reply_count": 0,
          "retweet_count": 0
        },
        "referenced_tweets": [
          {
            "id": "1985364959094620552",
            "type": "replied_to"
          }
        ],
        "reply_settings": "everyone",
        "text": "@IzayoiMarin 3,4反人类罪"
      },
      {
        "article": {},
        "attachments": {
          "poll_ids": [
            "1985364954417963008"
          ]
        },
        "author_id": "1870313420807163904",
        "conversation_id": "1985364959094620552",
        "created_at": "2025-11-03T15:14:27.000Z",
        "edit_controls": {
          "editable_until": "2025-11-03T16:14:27.000Z",
          "edits_remaining": 5,
          "is_edit_eligible": false
        },
        "edit_history_tweet_ids": [
          "1985364959094620552"
        ],
        "entities": {},
        "geo": {},
        "id": "1985364959094620552",
        "lang": "zh",
        "note_tweet": {
          "entities": {}
        },
        "possibly_sensitive": false,
        "public_metrics": {
          "bookmark_count": 4,
          "impression_count": 7577,
          "like_count": 78,
          "quote_count": 5,
          "reply_count": 49,
          "retweet_count": 1
        },
        "reply_settings": "everyone",
        "text": "你最反感哪个校规？"
      }
    ],
    "users": [
      {
        "created_at": "2024-09-26T11:19:31.000Z",
        "description": "私たちは二次元をこれほど熱愛している",
        "id": "1839263401845075974",
        "location": "Neoaurorium City",
        "name": "mortis",
        "pinned_tweet_id": "1895931291142627425",
        "profile_image_url": "https://pbs.twimg.com/profile_images/1971955303194546176/7EbSCYUF_normal.jpg",
        "protected": false,
        "public_metrics": {
          "followers_count": 1857,
          "following_count": 2503,
          "like_count": 21850,
          "listed_count": 9,
          "media_count": 311,
          "tweet_count": 8361
        },
        "username": "0Yowlry",
        "verified": false
      },
      {
        "created_at": "2024-12-21T03:40:57.000Z",
        "description": "09/高二（上学白天不在）/物化生/生理性别女/互fo/フォロバ99%/🇨🇳人/🇯🇵好き/挂：@soyorin_chihaya @quasoawa @Panther194466 @satochocolat17 @Baixiaoming2952 @NovaBabelo",
        "entities": {
          "description": {
            "mentions": [
              {
                "end": 63,
                "start": 47,
                "username": "soyorin_chihaya"
              },
              {
                "end": 73,
                "start": 64,
                "username": "quasoawa"
              },
              {
                "end": 88,
                "start": 74,
                "username": "Panther194466"
              },
              {
                "end": 104,
                "start": 89,
                "username": "satochocolat17"
              },
              {
                "end": 121,
                "start": 105,
                "username": "Baixiaoming2952"
              },
              {
                "end": 133,
                "start": 122,
                "username": "NovaBabelo"
              }
            ]
          },
          "url": {
            "urls": [
              {
                "display_url": "b23.tv/ep1449270",
                "end": 23,
                "expanded_url": "https://b23.tv/ep1449270",
                "start": 0,
                "url": "https://t.co/BABPQro7WH"
              }
            ]
          }
        },
        "id": "1870313420807163904",
        "location": "ダーリン、頑張って",
        "name": "まりん@絶対純愛101%",
        "pinned_tweet_id": "1984881752268042518",
        "profile_image_url": "https://pbs.twimg.com/profile_images/1979839146601426944/LBpfTPIa_normal.jpg",
        "protected": false,
        "public_metrics": {
          "followers_count": 1352,
          "following_count": 1711,
          "like_count": 26193,
          "listed_count": 4,
          "media_count": 972,
          "tweet_count": 12008
        },
        "url": "https://t.co/BABPQro7WH",
        "username": "IzayoiMarin",
        "verified": false
      }
    ]
  }
}