{
  "data": {
    "article": {},
    "attachments": {},
    "author_id": "1839263401845075974",
    "conversation_id": "1956314369584955469",
    "created_at": "2025-08-16T04:00:50.000Z",
    "edit_controls": {
      "editable_until": "2025-08-16T05:00:50.000Z",
      "edits_remaining": 5,
      "is_edit_eligible": false
    },
    "edit_history_tweet_ids": [
      "1956566799643759078"
    ],
    "entities": {
      "mentions": [
        {
          "end": 9,
          "id": "1811057149805834241",
          "start": 0,
          "username": "Tarimarl"
        }
      ]
    },
    "geo": {},
    "id": "1956566799643759078",
    "in_reply_to_user_id": "1811057149805834241",
    "lang": "ja",
    "note_tweet": {
      "entities": {}
    },
    "possibly_sensitive": false,
    "public_metrics": {
      "bookmark_count": 0,
      "impression_count": 0,
      "like_count": 0,
      "quote_count": 0,
      "reply_count": 0,
      "retweet_count": 0
    },
    "referenced_tweets": [
      {
        "id": "1956314369584955469",
        "type": "replied_to"
      }
    ],
    "reply_settings": "everyone",
    "text": "@Tarimarl 迫不及die"
  },
  "includes": {
    "tweets": [
      {
        "article": {},
        "attachments": {},
        "author_id": "1839263401845075974",
        "conversation_id": "1956314369584955469",
        "created_at": "2025-08-16T04:00:50.000Z",
        "edit_controls": {
          "editable_until": "2025-08-16T05:00:50.000Z",
          "edits_remaining": 5,
          "is_edit_eligible": false
        },
        "edit_history_tweet_ids": [
          "1956566799643759078"
        ],
        "entities": {
          "mentions": [
            {
              "end": 9,
              "id": "1811057149805834241",
              "start": 0,
              "username": "Tarimarl"
            }
          ]
        },
        "geo": {},
        "id": "1956566799643759078",
        "in_reply_to_user_id": "1811057149805834241",
        "lang": "ja",
        "note_tweet": {
          "entities": {}
        },
        "possibly_sensitive": false,
        "public_metrics": {
          "bookmark_count": 0,
          "impression_count": 0,
          "like_count": 0,
          "quote_count": 0,
          "reply_count": 0,
          "retweet_count": 0
        },
        "referenced_tweets": [
          {
            "id": "1956314369584955469",
            "type": "replied_to"
          }
        ],
        "reply_settings": "everyone",
        "text": "@Tarimarl 迫不及die"
      },
      {
        "article": {},
        "attachments": {},
        "author_id": "1811057149805834241",
        "conversation_id": "1956314369584955469",
        "created_at": "2025-08-15T11:17:46.000Z",
        "edit_controls": {
          "editable_until": "2025-08-15T12:17:46.000Z",
          "edits_remaining": 5,
          "is_edit_eligible": true
        },
        "edit_history_tweet_ids": [
          "1956314369584955469"
        ],
        "entities": {},
        "geo": {},
        "id": "1956314369584955469",
        "lang": "zh",
        "note_tweet": {
          "entities": {}
        },
        "possibly_sensitive": false,
        "public_metrics": {
          "bookmark_count": 21,
          "impression_count": 21834,
          "like_count": 580,
          "quote_count": 4,
          "reply_count": 21,
          "retweet_count": 32
        },
        "reply_settings": "everyone",
        "text": "如果您家孩子有以下这几种表现，那他这辈子就废了！\n1.去世\n2.走了\n3.死\n4.永眠\n5.见阎王\n6.上天堂\n7.下地狱\n8.卒\n9.亡\n10.丧生\n11.殁\n12.die"
      }
    ],
    "users": [
      {
        "created_at": "2024-09-26T11:19:31.000Z",
        "description": "私たちは二次元をこれほど熱愛している",
        "id": "1839263401845075974",
        "location": "Neoaurorium City",
        "name": "Yowlry",
        "pinned_tweet_id": "1895931291142627425",
        "profile_image_url": "https://pbs.twimg.com/profile_images/1900279853762392066/nf5oFqCF_normal.jpg",
        "protected": false,
        "public_metrics": {
          "followers_count": 1792,
          "following_count": 2393,
          "like_count": 17961,
          "listed_count": 7,
          "media_count": 294,
          "tweet_count": 7344
        },
        "username": "0Yowlry",
        "verified": false
      },
      {
        "created_at": "2024-07-10T15:17:40.000Z",
        "description": "一般高中生 | 性别是沃尔玛塑料袋 | 可以叫我小T/Ta一串字母巴拉巴拉 | 喜欢温柔聪明有趣的人 | 不吵架，不鉴证 | 什么都懂一点",
        "id": "1811057149805834241",
        "location": "✟​Heaven✟",
        "name": "Tarimar今天吃什么",
        "pinned_tweet_id": "1950150968143671410",
        "profile_image_url": "https://pbs.twimg.com/profile_images/1949484166711771136/ud5gOPeC_normal.jpg",
        "protected": false,
        "public_metrics": {
          "followers_count": 470,
          "following_count": 542,
          "like_count": 9205,
          "listed_count": 1,
          "media_count": 281,
          "tweet_count": 2623
        },
        "username": "Tarimarl",
        "verified": false
      }
    ]
  }
}