{
  "data": {
    "article": {},
    "attachments": {},
    "author_id": "1839263401845075974",
    "conversation_id": "1936041475856646518",
    "created_at": "2026-06-13T18:55:35.000Z",
    "edit_controls": {
      "editable_until": "2026-06-13T19:55:35.000Z",
      "edits_remaining": 5,
      "is_edit_eligible": false
    },
    "edit_history_tweet_ids": [
      "2065870715665211640"
    ],
    "entities": {
      "mentions": [
        {
          "end": 13,
          "id": "1756246342676979713",
          "start": 0,
          "username": "shungleemain"
        }
      ]
    },
    "geo": {},
    "id": "2065870715665211640",
    "in_reply_to_user_id": "1756246342676979713",
    "lang": "zh",
    "note_tweet": {
      "entities": {}
    },
    "possibly_sensitive": false,
    "public_metrics": {
      "bookmark_count": 0,
      "impression_count": 0,
      "like_count": 0,
      "quote_count": 0,
      "reply_count": 0,
      "retweet_count": 0
    },
    "referenced_tweets": [
      {
        "id": "1936042356756955617",
        "type": "replied_to"
      }
    ],
    "reply_settings": "everyone",
    "text": "@shungleemain 还能说话吗😁😁😁"
  },
  "includes": {
    "tweets": [
      {
        "article": {},
        "attachments": {},
        "author_id": "1839263401845075974",
        "conversation_id": "1936041475856646518",
        "created_at": "2026-06-13T18:55:35.000Z",
        "edit_controls": {
          "editable_until": "2026-06-13T19:55:35.000Z",
          "edits_remaining": 5,
          "is_edit_eligible": false
        },
        "edit_history_tweet_ids": [
          "2065870715665211640"
        ],
        "entities": {
          "mentions": [
            {
              "end": 13,
              "id": "1756246342676979713",
              "start": 0,
              "username": "shungleemain"
            }
          ]
        },
        "geo": {},
        "id": "2065870715665211640",
        "in_reply_to_user_id": "1756246342676979713",
        "lang": "zh",
        "note_tweet": {
          "entities": {}
        },
        "possibly_sensitive": false,
        "public_metrics": {
          "bookmark_count": 0,
          "impression_count": 0,
          "like_count": 0,
          "quote_count": 0,
          "reply_count": 0,
          "retweet_count": 0
        },
        "referenced_tweets": [
          {
            "id": "1936042356756955617",
            "type": "replied_to"
          }
        ],
        "reply_settings": "everyone",
        "text": "@shungleemain 还能说话吗😁😁😁"
      },
      {
        "article": {},
        "attachments": {},
        "author_id": "1756246342676979713",
        "conversation_id": "1936041475856646518",
        "created_at": "2025-06-20T12:44:02.000Z",
        "edit_controls": {
          "editable_until": "2025-06-20T13:44:02.000Z",
          "edits_remaining": 5,
          "is_edit_eligible": false
        },
        "edit_history_tweet_ids": [
          "1936042356756955617"
        ],
        "entities": {},
        "geo": {},
        "id": "1936042356756955617",
        "in_reply_to_user_id": "1915723009161375744",
        "lang": "ja",
        "note_tweet": {
          "entities": {}
        },
        "possibly_sensitive": false,
        "public_metrics": {
          "bookmark_count": 0,
          "impression_count": 53,
          "like_count": 2,
          "quote_count": 0,
          "reply_count": 3,
          "retweet_count": 0
        },
        "referenced_tweets": [
          {
            "id": "1936042066553061424",
            "type": "replied_to"
          }
        ],
        "reply_settings": "everyone",
        "text": "@fuckpregabalin 「他」是誰？是微信 ID：  hainengshuohuama嗎？"
      }
    ],
    "users": [
      {
        "created_at": "2024-09-26T11:19:31.000Z",
        "description": "私たちは二次元をこれほど熱愛している \n\n🇦🇶🇦🇶🇦🇶",
        "id": "1839263401845075974",
        "location": "Neoaurorium City",
        "name": "mortis",
        "pinned_tweet_id": "1895931291142627425",
        "profile_image_url": "https://pbs.twimg.com/profile_images/1971955303194546176/7EbSCYUF_normal.jpg",
        "protected": false,
        "public_metrics": {
          "followers_count": 2101,
          "following_count": 3049,
          "like_count": 39623,
          "listed_count": 10,
          "media_count": 364,
          "tweet_count": 12537
        },
        "username": "0Yowlry",
        "verified": false
      },
      {
        "created_at": "2024-02-10T09:19:19.000Z",
        "description": "超級好詭秘 @Akinoyo_desu\n可愛的蜜獾 @kittymi030\n可愛的Mercy @Mercyvnv",
        "entities": {
          "description": {
            "mentions": [
              {
                "end": 19,
                "start": 6,
                "username": "Akinoyo_desu"
              },
              {
                "end": 37,
                "start": 26,
                "username": "kittymi030"
              },
              {
                "end": 56,
                "start": 47,
                "username": "Mercyvnv"
              }
            ]
          },
          "url": {
            "urls": [
              {
                "display_url": "t.me/shungleemain",
                "end": 23,
                "expanded_url": "https://t.me/shungleemain",
                "start": 0,
                "url": "https://t.co/ZWd7sZXvOA"
              }
            ]
          }
        },
        "id": "1756246342676979713",
        "location": "來看生力麵的TG→",
        "name": "聖米格爾生力麵",
        "profile_image_url": "https://pbs.twimg.com/profile_images/2041138223767003137/717JFCWp_normal.jpg",
        "protected": false,
        "public_metrics": {
          "followers_count": 2289,
          "following_count": 617,
          "like_count": 2823,
          "listed_count": 7,
          "media_count": 594,
          "tweet_count": 6873
        },
        "url": "https://t.co/ZWd7sZXvOA",
        "username": "shungleemain",
        "verified": false
      }
    ]
  }
}