{
  "data": {
    "article": {},
    "attachments": {},
    "author_id": "1839263401845075974",
    "conversation_id": "2050612191548825768",
    "created_at": "2026-05-05T07:58:54.000Z",
    "edit_controls": {
      "editable_until": "2026-05-05T08:58:54.000Z",
      "edits_remaining": 5,
      "is_edit_eligible": false
    },
    "edit_history_tweet_ids": [
      "2051572331336827112"
    ],
    "entities": {
      "mentions": [
        {
          "end": 11,
          "id": "1841429529413529600",
          "start": 0,
          "username": "LazyCataww"
        }
      ]
    },
    "geo": {},
    "id": "2051572331336827112",
    "in_reply_to_user_id": "1841429529413529600",
    "lang": "zh",
    "note_tweet": {
      "entities": {}
    },
    "possibly_sensitive": false,
    "public_metrics": {
      "bookmark_count": 0,
      "impression_count": 0,
      "like_count": 0,
      "quote_count": 0,
      "reply_count": 0,
      "retweet_count": 0
    },
    "referenced_tweets": [
      {
        "id": "2050612191548825768",
        "type": "replied_to"
      }
    ],
    "reply_settings": "everyone",
    "text": "@LazyCataww 你是不是还有一个号"
  },
  "includes": {
    "media": [
      {
        "height": 1024,
        "media_key": "3_2050612177007185920",
        "public_metrics": {},
        "type": "photo",
        "url": "https://pbs.twimg.com/media/HHU86Q6akAAR5aD.jpg",
        "width": 600
      },
      {
        "height": 1429,
        "media_key": "3_2050612177028165632",
        "public_metrics": {},
        "type": "photo",
        "url": "https://pbs.twimg.com/media/HHU86Q_asAAL3y9.jpg",
        "width": 1125
      },
      {
        "height": 863,
        "media_key": "3_2050612177036546048",
        "public_metrics": {},
        "type": "photo",
        "url": "https://pbs.twimg.com/media/HHU86RBakAABonY.jpg",
        "width": 772
      },
      {
        "height": 1152,
        "media_key": "3_2050612177040789504",
        "public_metrics": {},
        "type": "photo",
        "url": "https://pbs.twimg.com/media/HHU86RCbUAAVWch.jpg",
        "width": 1152
      }
    ],
    "tweets": [
      {
        "article": {},
        "attachments": {},
        "author_id": "1839263401845075974",
        "conversation_id": "2050612191548825768",
        "created_at": "2026-05-05T07:58:54.000Z",
        "edit_controls": {
          "editable_until": "2026-05-05T08:58:54.000Z",
          "edits_remaining": 5,
          "is_edit_eligible": false
        },
        "edit_history_tweet_ids": [
          "2051572331336827112"
        ],
        "entities": {
          "mentions": [
            {
              "end": 11,
              "id": "1841429529413529600",
              "start": 0,
              "username": "LazyCataww"
            }
          ]
        },
        "geo": {},
        "id": "2051572331336827112",
        "in_reply_to_user_id": "1841429529413529600",
        "lang": "zh",
        "note_tweet": {
          "entities": {}
        },
        "possibly_sensitive": false,
        "public_metrics": {
          "bookmark_count": 0,
          "impression_count": 0,
          "like_count": 0,
          "quote_count": 0,
          "reply_count": 0,
          "retweet_count": 0
        },
        "referenced_tweets": [
          {
            "id": "2050612191548825768",
            "type": "replied_to"
          }
        ],
        "reply_settings": "everyone",
        "text": "@LazyCataww 你是不是还有一个号"
      },
      {
        "article": {},
        "attachments": {
          "media_keys": [
            "3_2050612177007185920",
            "3_2050612177028165632",
            "3_2050612177036546048",
            "3_2050612177040789504"
          ]
        },
        "author_id": "1841429529413529600",
        "conversation_id": "2050612191548825768",
        "created_at": "2026-05-02T16:23:39.000Z",
        "edit_controls": {
          "editable_until": "2026-05-02T17:23:39.000Z",
          "edits_remaining": 5,
          "is_edit_eligible": false
        },
        "edit_history_tweet_ids": [
          "2050612191548825768"
        ],
        "entities": {
          "urls": [
            {
              "display_url": "pic.x.com/ObqyNXowlE",
              "end": 150,
              "expanded_url": "https://x.com/LazyCataww/status/2050612191548825768/photo/1",
              "media_key": "3_2050612177007185920",
              "start": 127,
              "url": "https://t.co/ObqyNXowlE"
            },
            {
              "display_url": "pic.x.com/ObqyNXowlE",
              "end": 150,
              "expanded_url": "https://x.com/LazyCataww/status/2050612191548825768/photo/1",
              "media_key": "3_2050612177028165632",
              "start": 127,
              "url": "https://t.co/ObqyNXowlE"
            },
            {
              "display_url": "pic.x.com/ObqyNXowlE",
              "end": 150,
              "expanded_url": "https://x.com/LazyCataww/status/2050612191548825768/photo/1",
              "media_key": "3_2050612177036546048",
              "start": 127,
              "url": "https://t.co/ObqyNXowlE"
            },
            {
              "display_url": "pic.x.com/ObqyNXowlE",
              "end": 150,
              "expanded_url": "https://x.com/LazyCataww/status/2050612191548825768/photo/1",
              "media_key": "3_2050612177040789504",
              "start": 127,
              "url": "https://t.co/ObqyNXowlE"
            }
          ]
        },
        "geo": {},
        "id": "2050612191548825768",
        "lang": "zh",
        "note_tweet": {
          "entities": {}
        },
        "possibly_sensitive": false,
        "public_metrics": {
          "bookmark_count": 1,
          "impression_count": 565,
          "like_count": 11,
          "quote_count": 0,
          "reply_count": 3,
          "retweet_count": 0
        },
        "reply_settings": "everyone",
        "text": "guys\n这是我……\n当作新朋友认识吧\n之前我号炸了\n嗯好死\n所以这是新的账号\n希望你们还记得我\n谢谢喵\n以及我收款码在这……\n有钱了想给我爆的话谢谢你们\n虽然你们都把钱给别的长发男短发女了\n为什么是长发男短发女\n因为我喜欢🤓\n苦逼高中生长发还是算了（ https://t.co/ObqyNXowlE"
      }
    ],
    "users": [
      {
        "created_at": "2024-09-26T11:19:31.000Z",
        "description": "私たちは二次元をこれほど熱愛している \n\n🇦🇶🇦🇶🇦🇶",
        "id": "1839263401845075974",
        "location": "Neoaurorium City",
        "name": "mortis",
        "pinned_tweet_id": "1895931291142627425",
        "profile_image_url": "https://pbs.twimg.com/profile_images/1971955303194546176/7EbSCYUF_normal.jpg",
        "protected": false,
        "public_metrics": {
          "followers_count": 1971,
          "following_count": 2783,
          "like_count": 30583,
          "listed_count": 10,
          "media_count": 336,
          "tweet_count": 10526
        },
        "username": "0Yowlry",
        "verified": false
      },
      {
        "created_at": "2024-10-02T10:46:34.000Z",
        "description": "emm\n对\n大号G了小号接着炒作",
        "id": "1841429529413529600",
        "name": "天雨（魔乐）",
        "pinned_tweet_id": "2050612191548825768",
        "profile_image_url": "https://pbs.twimg.com/profile_images/2051214180745650176/YgDV8phI_normal.jpg",
        "protected": false,
        "public_metrics": {
          "followers_count": 255,
          "following_count": 268,
          "like_count": 6007,
          "listed_count": 0,
          "media_count": 101,
          "tweet_count": 1726
        },
        "username": "LazyCataww",
        "verified": false
      }
    ]
  }
}