{
  "data": {
    "article": {},
    "attachments": {
      "media_keys": [
        "3_2064245625710161920",
        "3_2064245625672368128",
        "3_2064245626830041088"
      ],
      "media_source_tweet_id": [
        "2064245629812089244",
        "2064245629812089244",
        "2064245629812089244"
      ]
    },
    "author_id": "1839263401845075974",
    "conversation_id": "2064674937965781317",
    "created_at": "2026-06-10T11:43:59.000Z",
    "edit_controls": {
      "editable_until": "2026-06-10T12:43:59.000Z",
      "edits_remaining": 5,
      "is_edit_eligible": false
    },
    "edit_history_tweet_ids": [
      "2064674937965781317"
    ],
    "entities": {
      "mentions": [
        {
          "end": 16,
          "id": "1462403736890920963",
          "start": 3,
          "username": "oekaki_bibbi"
        }
      ],
      "urls": [
        {
          "display_url": "pic.x.com/TMDXR92F63",
          "end": 51,
          "expanded_url": "https://x.com/oekaki_bibbi/status/2064245629812089244/photo/1",
          "media_key": "3_2064245625710161920",
          "start": 28,
          "url": "https://t.co/TMDXR92F63"
        },
        {
          "display_url": "pic.x.com/TMDXR92F63",
          "end": 51,
          "expanded_url": "https://x.com/oekaki_bibbi/status/2064245629812089244/photo/1",
          "media_key": "3_2064245625672368128",
          "start": 28,
          "url": "https://t.co/TMDXR92F63"
        },
        {
          "display_url": "pic.x.com/TMDXR92F63",
          "end": 51,
          "expanded_url": "https://x.com/oekaki_bibbi/status/2064245629812089244/photo/1",
          "media_key": "3_2064245626830041088",
          "start": 28,
          "url": "https://t.co/TMDXR92F63"
        }
      ]
    },
    "geo": {},
    "id": "2064674937965781317",
    "lang": "ja",
    "note_tweet": {
      "entities": {}
    },
    "possibly_sensitive": false,
    "public_metrics": {
      "bookmark_count": 0,
      "impression_count": 0,
      "like_count": 0,
      "quote_count": 0,
      "reply_count": 0,
      "retweet_count": 660
    },
    "referenced_tweets": [
      {
        "id": "2064245629812089244",
        "type": "retweeted"
      }
    ],
    "reply_settings": "everyone",
    "text": "RT @oekaki_bibbi: 密着っていいよね😉 https://t.co/TMDXR92F63"
  },
  "includes": {
    "media": [
      {
        "height": 2750,
        "media_key": "3_2064245625710161920",
        "public_metrics": {},
        "type": "photo",
        "url": "https://pbs.twimg.com/media/HKWsdbGbsAAqjEC.jpg",
        "width": 2750
      },
      {
        "height": 3072,
        "media_key": "3_2064245625672368128",
        "public_metrics": {},
        "type": "photo",
        "url": "https://pbs.twimg.com/media/HKWsda9bAAAHWlG.jpg",
        "width": 2420
      },
      {
        "height": 3070,
        "media_key": "3_2064245626830041088",
        "public_metrics": {},
        "type": "photo",
        "url": "https://pbs.twimg.com/media/HKWsdfRbsAAg9I_.jpg",
        "width": 2250
      }
    ],
    "tweets": [
      {
        "article": {},
        "attachments": {
          "media_keys": [
            "3_2064245625710161920",
            "3_2064245625672368128",
            "3_2064245626830041088"
          ],
          "media_source_tweet_id": [
            "2064245629812089244",
            "2064245629812089244",
            "2064245629812089244"
          ]
        },
        "author_id": "1839263401845075974",
        "conversation_id": "2064674937965781317",
        "created_at": "2026-06-10T11:43:59.000Z",
        "edit_controls": {
          "editable_until": "2026-06-10T12:43:59.000Z",
          "edits_remaining": 5,
          "is_edit_eligible": false
        },
        "edit_history_tweet_ids": [
          "2064674937965781317"
        ],
        "entities": {
          "mentions": [
            {
              "end": 16,
              "id": "1462403736890920963",
              "start": 3,
              "username": "oekaki_bibbi"
            }
          ],
          "urls": [
            {
              "display_url": "pic.x.com/TMDXR92F63",
              "end": 51,
              "expanded_url": "https://x.com/oekaki_bibbi/status/2064245629812089244/photo/1",
              "media_key": "3_2064245625710161920",
              "start": 28,
              "url": "https://t.co/TMDXR92F63"
            },
            {
              "display_url": "pic.x.com/TMDXR92F63",
              "end": 51,
              "expanded_url": "https://x.com/oekaki_bibbi/status/2064245629812089244/photo/1",
              "media_key": "3_2064245625672368128",
              "start": 28,
              "url": "https://t.co/TMDXR92F63"
            },
            {
              "display_url": "pic.x.com/TMDXR92F63",
              "end": 51,
              "expanded_url": "https://x.com/oekaki_bibbi/status/2064245629812089244/photo/1",
              "media_key": "3_2064245626830041088",
              "start": 28,
              "url": "https://t.co/TMDXR92F63"
            }
          ]
        },
        "geo": {},
        "id": "2064674937965781317",
        "lang": "ja",
        "note_tweet": {
          "entities": {}
        },
        "possibly_sensitive": false,
        "public_metrics": {
          "bookmark_count": 0,
          "impression_count": 0,
          "like_count": 0,
          "quote_count": 0,
          "reply_count": 0,
          "retweet_count": 660
        },
        "referenced_tweets": [
          {
            "id": "2064245629812089244",
            "type": "retweeted"
          }
        ],
        "reply_settings": "everyone",
        "text": "RT @oekaki_bibbi: 密着っていいよね😉 https://t.co/TMDXR92F63"
      },
      {
        "article": {},
        "attachments": {
          "media_keys": [
            "3_2064245625710161920",
            "3_2064245625672368128",
            "3_2064245626830041088"
          ]
        },
        "author_id": "1462403736890920963",
        "conversation_id": "2064245629812089244",
        "created_at": "2026-06-09T07:18:04.000Z",
        "edit_controls": {
          "editable_until": "2026-06-09T08:18:04.000Z",
          "edits_remaining": 5,
          "is_edit_eligible": true
        },
        "edit_history_tweet_ids": [
          "2064245629812089244"
        ],
        "entities": {
          "urls": [
            {
              "display_url": "pic.x.com/TMDXR92F63",
              "end": 33,
              "expanded_url": "https://x.com/oekaki_bibbi/status/2064245629812089244/photo/1",
              "media_key": "3_2064245625710161920",
              "start": 10,
              "url": "https://t.co/TMDXR92F63"
            },
            {
              "display_url": "pic.x.com/TMDXR92F63",
              "end": 33,
              "expanded_url": "https://x.com/oekaki_bibbi/status/2064245629812089244/photo/1",
              "media_key": "3_2064245625672368128",
              "start": 10,
              "url": "https://t.co/TMDXR92F63"
            },
            {
              "display_url": "pic.x.com/TMDXR92F63",
              "end": 33,
              "expanded_url": "https://x.com/oekaki_bibbi/status/2064245629812089244/photo/1",
              "media_key": "3_2064245626830041088",
              "start": 10,
              "url": "https://t.co/TMDXR92F63"
            }
          ]
        },
        "geo": {},
        "id": "2064245629812089244",
        "lang": "ja",
        "note_tweet": {
          "entities": {}
        },
        "possibly_sensitive": false,
        "public_metrics": {
          "bookmark_count": 541,
          "impression_count": 64905,
          "like_count": 5857,
          "quote_count": 7,
          "reply_count": 20,
          "retweet_count": 660
        },
        "reply_settings": "everyone",
        "text": "密着っていいよね😉 https://t.co/TMDXR92F63"
      }
    ],
    "users": [
      {
        "created_at": "2024-09-26T11:19:31.000Z",
        "description": "私たちは二次元をこれほど熱愛している \n\n🇦🇶🇦🇶🇦🇶",
        "id": "1839263401845075974",
        "location": "Neoaurorium City",
        "name": "mortis",
        "pinned_tweet_id": "1895931291142627425",
        "profile_image_url": "https://pbs.twimg.com/profile_images/1971955303194546176/7EbSCYUF_normal.jpg",
        "protected": false,
        "public_metrics": {
          "followers_count": 2086,
          "following_count": 2987,
          "like_count": 37971,
          "listed_count": 10,
          "media_count": 367,
          "tweet_count": 12266
        },
        "username": "0Yowlry",
        "verified": false
      },
      {
        "created_at": "2021-11-21T12:53:24.000Z",
        "description": "好きな絵を描く",
        "id": "1462403736890920963",
        "name": "まよ",
        "pinned_tweet_id": "1669238935007141888",
        "profile_image_url": "https://pbs.twimg.com/profile_images/1893993268624478208/saa_9fza_normal.jpg",
        "protected": false,
        "public_metrics": {
          "followers_count": 122680,
          "following_count": 272,
          "like_count": 22462,
          "listed_count": 562,
          "media_count": 637,
          "tweet_count": 15903
        },
        "username": "oekaki_bibbi",
        "verified": true
      }
    ]
  }
}