{
  "data": {
    "article": {},
    "attachments": {},
    "author_id": "1839263401845075974",
    "conversation_id": "2067261297365028964",
    "created_at": "2026-06-17T18:23:06.000Z",
    "edit_controls": {
      "editable_until": "2026-06-17T19:23:06.000Z",
      "edits_remaining": 5,
      "is_edit_eligible": false
    },
    "edit_history_tweet_ids": [
      "2067312093678952831"
    ],
    "entities": {
      "mentions": [
        {
          "end": 10,
          "id": "1946642385028718592",
          "start": 0,
          "username": "kurabakei"
        }
      ]
    },
    "geo": {},
    "id": "2067312093678952831",
    "in_reply_to_user_id": "1946642385028718592",
    "lang": "zh",
    "note_tweet": {
      "entities": {}
    },
    "possibly_sensitive": false,
    "public_metrics": {
      "bookmark_count": 0,
      "impression_count": 0,
      "like_count": 0,
      "quote_count": 0,
      "reply_count": 0,
      "retweet_count": 0
    },
    "referenced_tweets": [
      {
        "id": "2067261297365028964",
        "type": "replied_to"
      }
    ],
    "reply_settings": "everyone",
    "text": "@kurabakei 感觉你要开着sps睡着（"
  },
  "includes": {
    "tweets": [
      {
        "article": {},
        "attachments": {},
        "author_id": "1839263401845075974",
        "conversation_id": "2067261297365028964",
        "created_at": "2026-06-17T18:23:06.000Z",
        "edit_controls": {
          "editable_until": "2026-06-17T19:23:06.000Z",
          "edits_remaining": 5,
          "is_edit_eligible": false
        },
        "edit_history_tweet_ids": [
          "2067312093678952831"
        ],
        "entities": {
          "mentions": [
            {
              "end": 10,
              "id": "1946642385028718592",
              "start": 0,
              "username": "kurabakei"
            }
          ]
        },
        "geo": {},
        "id": "2067312093678952831",
        "in_reply_to_user_id": "1946642385028718592",
        "lang": "zh",
        "note_tweet": {
          "entities": {}
        },
        "possibly_sensitive": false,
        "public_metrics": {
          "bookmark_count": 0,
          "impression_count": 0,
          "like_count": 0,
          "quote_count": 0,
          "reply_count": 0,
          "retweet_count": 0
        },
        "referenced_tweets": [
          {
            "id": "2067261297365028964",
            "type": "replied_to"
          }
        ],
        "reply_settings": "everyone",
        "text": "@kurabakei 感觉你要开着sps睡着（"
      },
      {
        "article": {},
        "attachments": {},
        "author_id": "1946642385028718592",
        "conversation_id": "2067261297365028964",
        "created_at": "2026-06-17T15:01:15.000Z",
        "edit_controls": {
          "editable_until": "2026-06-17T16:01:15.000Z",
          "edits_remaining": 5,
          "is_edit_eligible": true
        },
        "edit_history_tweet_ids": [
          "2067261297365028964"
        ],
        "entities": {
          "urls": [
            {
              "description": "闇葉’s Space · 0 listening · Where live audio conversations happen",
              "display_url": "x.com/i/spaces/1RKjp…",
              "end": 23,
              "expanded_url": "https://x.com/i/spaces/1RKjppWdrneJw",
              "start": 0,
              "status": 200,
              "title": "Happening now: 等藥效中💊",
              "unwound_url": "https://twitter.com/i/spaces/1RKjppWdrneJw/peek",
              "url": "https://t.co/kXY8w8Q7ik"
            }
          ]
        },
        "geo": {},
        "id": "2067261297365028964",
        "lang": "zxx",
        "note_tweet": {
          "entities": {}
        },
        "possibly_sensitive": false,
        "public_metrics": {
          "bookmark_count": 1,
          "impression_count": 332,
          "like_count": 4,
          "quote_count": 0,
          "reply_count": 25,
          "retweet_count": 0
        },
        "reply_settings": "everyone",
        "text": "https://t.co/kXY8w8Q7ik"
      }
    ],
    "users": [
      {
        "created_at": "2024-09-26T11:19:31.000Z",
        "description": "私たちは二次元をこれほど熱愛している \n\n🇦🇶🇦🇶🇦🇶",
        "id": "1839263401845075974",
        "location": "Neoaurorium City",
        "name": "mortis",
        "pinned_tweet_id": "1895931291142627425",
        "profile_image_url": "https://pbs.twimg.com/profile_images/1971955303194546176/7EbSCYUF_normal.jpg",
        "protected": false,
        "public_metrics": {
          "followers_count": 2113,
          "following_count": 3083,
          "like_count": 40432,
          "listed_count": 10,
          "media_count": 367,
          "tweet_count": 12766
        },
        "username": "0Yowlry",
        "verified": false
      },
      {
        "created_at": "2025-07-19T18:44:58.000Z",
        "description": "病み垢/リスカ/09/地雷女子/メンヘラ🚪188\nMy savior is you, for whom I owe my life.",
        "id": "1946642385028718592",
        "location": "地獄",
        "name": "闇葉",
        "pinned_tweet_id": "1976750551363981816",
        "profile_image_url": "https://pbs.twimg.com/profile_images/2038986594074718209/txD_t6sc_normal.jpg",
        "protected": false,
        "public_metrics": {
          "followers_count": 963,
          "following_count": 454,
          "like_count": 2753,
          "listed_count": 2,
          "media_count": 133,
          "tweet_count": 708
        },
        "username": "kurabakei",
        "verified": false
      }
    ]
  }
}