{
  "data": {
    "article": {},
    "attachments": {},
    "author_id": "1839263401845075974",
    "conversation_id": "2039137802626195539",
    "created_at": "2026-04-07T11:54:33.000Z",
    "edit_controls": {
      "editable_until": "2026-04-07T12:54:33.000Z",
      "edits_remaining": 5,
      "is_edit_eligible": false
    },
    "edit_history_tweet_ids": [
      "2041484774058205316"
    ],
    "entities": {
      "mentions": [
        {
          "end": 15,
          "id": "1886965038608736256",
          "start": 0,
          "username": "yangyang200413"
        }
      ]
    },
    "geo": {},
    "id": "2041484774058205316",
    "in_reply_to_user_id": "1886965038608736256",
    "lang": "qme",
    "note_tweet": {
      "entities": {}
    },
    "possibly_sensitive": false,
    "public_metrics": {
      "bookmark_count": 0,
      "impression_count": 0,
      "like_count": 0,
      "quote_count": 0,
      "reply_count": 0,
      "retweet_count": 0
    },
    "referenced_tweets": [
      {
        "id": "2039137802626195539",
        "type": "replied_to"
      }
    ],
    "reply_settings": "everyone",
    "text": "@yangyang200413 🤤"
  },
  "includes": {
    "media": [
      {
        "height": 2048,
        "media_key": "3_2039137794375999489",
        "public_metrics": {},
        "type": "photo",
        "url": "https://pbs.twimg.com/media/HEx5BSna4AExPbV.jpg",
        "width": 1152
      }
    ],
    "tweets": [
      {
        "article": {},
        "attachments": {},
        "author_id": "1839263401845075974",
        "conversation_id": "2039137802626195539",
        "created_at": "2026-04-07T11:54:33.000Z",
        "edit_controls": {
          "editable_until": "2026-04-07T12:54:33.000Z",
          "edits_remaining": 5,
          "is_edit_eligible": false
        },
        "edit_history_tweet_ids": [
          "2041484774058205316"
        ],
        "entities": {
          "mentions": [
            {
              "end": 15,
              "id": "1886965038608736256",
              "start": 0,
              "username": "yangyang200413"
            }
          ]
        },
        "geo": {},
        "id": "2041484774058205316",
        "in_reply_to_user_id": "1886965038608736256",
        "lang": "qme",
        "note_tweet": {
          "entities": {}
        },
        "possibly_sensitive": false,
        "public_metrics": {
          "bookmark_count": 0,
          "impression_count": 0,
          "like_count": 0,
          "quote_count": 0,
          "reply_count": 0,
          "retweet_count": 0
        },
        "referenced_tweets": [
          {
            "id": "2039137802626195539",
            "type": "replied_to"
          }
        ],
        "reply_settings": "everyone",
        "text": "@yangyang200413 🤤"
      },
      {
        "article": {},
        "attachments": {
          "media_keys": [
            "3_2039137794375999489"
          ]
        },
        "author_id": "1886965038608736256",
        "conversation_id": "2039137802626195539",
        "created_at": "2026-04-01T00:28:32.000Z",
        "edit_controls": {
          "editable_until": "2026-04-01T01:28:32.000Z",
          "edits_remaining": 5,
          "is_edit_eligible": true
        },
        "edit_history_tweet_ids": [
          "2039137802626195539"
        ],
        "entities": {
          "hashtags": [
            {
              "end": 8,
              "start": 5,
              "tag": "男娘"
            }
          ],
          "urls": [
            {
              "display_url": "pic.x.com/QsXBPmsFYn",
              "end": 32,
              "expanded_url": "https://x.com/yangyang200413/status/2039137802626195539/photo/1",
              "media_key": "3_2039137794375999489",
              "start": 9,
              "url": "https://t.co/QsXBPmsFYn"
            }
          ]
        },
        "geo": {},
        "id": "2039137802626195539",
        "lang": "zh",
        "note_tweet": {
          "entities": {}
        },
        "possibly_sensitive": false,
        "public_metrics": {
          "bookmark_count": 1,
          "impression_count": 2192,
          "like_count": 21,
          "quote_count": 0,
          "reply_count": 4,
          "retweet_count": 0
        },
        "reply_settings": "everyone",
        "text": "吃我一脚 #男娘 https://t.co/QsXBPmsFYn"
      }
    ],
    "users": [
      {
        "created_at": "2024-09-26T11:19:31.000Z",
        "description": "私たちは二次元をこれほど熱愛している",
        "id": "1839263401845075974",
        "location": "Neoaurorium City",
        "name": "mortis",
        "pinned_tweet_id": "1895931291142627425",
        "profile_image_url": "https://pbs.twimg.com/profile_images/1971955303194546176/7EbSCYUF_normal.jpg",
        "protected": false,
        "public_metrics": {
          "followers_count": 1894,
          "following_count": 2638,
          "like_count": 27310,
          "listed_count": 11,
          "media_count": 327,
          "tweet_count": 9710
        },
        "username": "0Yowlry",
        "verified": false
      },
      {
        "created_at": "2025-02-05T02:28:34.000Z",
        "description": "femboy💕/SPQR/求fo💗/mo3/Apex Legends             \n关注yangyang谢谢喵，每日美图敬请期待！",
        "id": "1886965038608736256",
        "location": "维爱",
        "name": "yangyang",
        "pinned_tweet_id": "2040224155359187315",
        "profile_image_url": "https://pbs.twimg.com/profile_images/2038541972621991936/eEV8Il3N_normal.jpg",
        "protected": false,
        "public_metrics": {
          "followers_count": 577,
          "following_count": 99,
          "like_count": 1467,
          "listed_count": 1,
          "media_count": 79,
          "tweet_count": 585
        },
        "username": "yangyang200413",
        "verified": false
      }
    ]
  }
}