{
  "data": {
    "article": {},
    "attachments": {},
    "author_id": "1839263401845075974",
    "conversation_id": "2076717926066106501",
    "created_at": "2026-07-13T22:10:07.000Z",
    "edit_controls": {
      "editable_until": "2026-07-13T23:10:07.000Z",
      "edits_remaining": 5,
      "is_edit_eligible": false
    },
    "edit_history_tweet_ids": [
      "2076791308816126280"
    ],
    "entities": {
      "mentions": [
        {
          "end": 9,
          "id": "1242074475400548352",
          "start": 0,
          "username": "A1oneSKy"
        }
      ]
    },
    "geo": {},
    "id": "2076791308816126280",
    "in_reply_to_user_id": "1242074475400548352",
    "lang": "qme",
    "note_tweet": {
      "entities": {}
    },
    "possibly_sensitive": false,
    "public_metrics": {
      "bookmark_count": 0,
      "impression_count": 0,
      "like_count": 0,
      "quote_count": 0,
      "reply_count": 0,
      "retweet_count": 0
    },
    "referenced_tweets": [
      {
        "id": "2076717926066106501",
        "type": "replied_to"
      }
    ],
    "reply_settings": "everyone",
    "text": "@A1oneSKy 🤤"
  },
  "includes": {
    "media": [
      {
        "height": 3072,
        "media_key": "3_2076717917702660096",
        "public_metrics": {},
        "type": "photo",
        "url": "https://pbs.twimg.com/media/HNH78XdbIAAot5F.jpg",
        "width": 4096
      }
    ],
    "tweets": [
      {
        "article": {},
        "attachments": {},
        "author_id": "1839263401845075974",
        "conversation_id": "2076717926066106501",
        "created_at": "2026-07-13T22:10:07.000Z",
        "edit_controls": {
          "editable_until": "2026-07-13T23:10:07.000Z",
          "edits_remaining": 5,
          "is_edit_eligible": false
        },
        "edit_history_tweet_ids": [
          "2076791308816126280"
        ],
        "entities": {
          "mentions": [
            {
              "end": 9,
              "id": "1242074475400548352",
              "start": 0,
              "username": "A1oneSKy"
            }
          ]
        },
        "geo": {},
        "id": "2076791308816126280",
        "in_reply_to_user_id": "1242074475400548352",
        "lang": "qme",
        "note_tweet": {
          "entities": {}
        },
        "possibly_sensitive": false,
        "public_metrics": {
          "bookmark_count": 0,
          "impression_count": 0,
          "like_count": 0,
          "quote_count": 0,
          "reply_count": 0,
          "retweet_count": 0
        },
        "referenced_tweets": [
          {
            "id": "2076717926066106501",
            "type": "replied_to"
          }
        ],
        "reply_settings": "everyone",
        "text": "@A1oneSKy 🤤"
      },
      {
        "article": {},
        "attachments": {
          "media_keys": [
            "3_2076717917702660096"
          ]
        },
        "author_id": "1242074475400548352",
        "context_annotations": [
          {
            "domain": {
              "description": "Categories within Brand Verticals that narrow down the scope of Brands",
              "id": "46",
              "name": "Business Taxonomy"
            },
            "entity": {
              "description": "Brands, companies, advertisers and every non-person handle with the profit intent and related to foods & beverages such as snacks, soft drinks, beers.",
              "id": "1557696888568045569",
              "name": "Food & Beverage Business"
            }
          }
        ],
        "conversation_id": "2076717926066106501",
        "created_at": "2026-07-13T17:18:31.000Z",
        "edit_controls": {
          "editable_until": "2026-07-13T18:18:31.000Z",
          "edits_remaining": 5,
          "is_edit_eligible": true
        },
        "edit_history_tweet_ids": [
          "2076717926066106501"
        ],
        "entities": {
          "urls": [
            {
              "display_url": "pic.x.com/t2oFOfliRc",
              "end": 45,
              "expanded_url": "https://x.com/A1oneSKy/status/2076717926066106501/photo/1",
              "media_key": "3_2076717917702660096",
              "start": 22,
              "url": "https://t.co/t2oFOfliRc"
            }
          ]
        },
        "geo": {},
        "id": "2076717926066106501",
        "lang": "zh",
        "note_tweet": {
          "entities": {}
        },
        "possibly_sensitive": false,
        "public_metrics": {
          "bookmark_count": 0,
          "impression_count": 316,
          "like_count": 19,
          "quote_count": 0,
          "reply_count": 5,
          "retweet_count": 0
        },
        "reply_settings": "everyone",
        "text": "加个餐\n不知道这个叫什么反正看起来挺好吃的 https://t.co/t2oFOfliRc"
      }
    ],
    "users": [
      {
        "created_at": "2024-09-26T11:19:31.000Z",
        "description": "Anime | Minecraft | Aerospace | Girls Band | Game | Journey | Natural Science",
        "id": "1839263401845075974",
        "location": "Neoaurorium City",
        "name": "mortis",
        "pinned_tweet_id": "2067658335088943417",
        "profile_image_url": "https://pbs.twimg.com/profile_images/1971955303194546176/7EbSCYUF_normal.jpg",
        "protected": false,
        "public_metrics": {
          "followers_count": 2255,
          "following_count": 3358,
          "like_count": 47895,
          "listed_count": 10,
          "media_count": 383,
          "tweet_count": 14880
        },
        "url": "",
        "username": "0Yowlry",
        "verified": false
      },
      {
        "created_at": "2020-03-23T13:03:36.000Z",
        "description": "EN / CN / JP / KR/ 韓國語 계정@alonesky_kr ㅣ 生命体征维持中ㅣ路边一条\n專攻은 電子工學 | 宝宝@mario_2333",
        "entities": {
          "description": {
            "mentions": [
              {
                "end": 37,
                "start": 25,
                "username": "alonesky_kr"
              },
              {
                "end": 77,
                "start": 66,
                "username": "mario_2333"
              }
            ]
          },
          "url": {
            "urls": [
              {
                "display_url": "alonesky.moe",
                "end": 23,
                "expanded_url": "https://alonesky.moe",
                "start": 0,
                "url": "https://t.co/b8Rzwcvm1z"
              }
            ]
          }
        },
        "id": "1242074475400548352",
        "name": "𝓐𝓛𝓸𝓷𝓮𝓢𝓚𝔂",
        "pinned_tweet_id": "1567905692379664384",
        "profile_image_url": "https://pbs.twimg.com/profile_images/2061452830142283776/kIazC4sW_normal.jpg",
        "protected": false,
        "public_metrics": {
          "followers_count": 1432,
          "following_count": 1733,
          "like_count": 8603,
          "listed_count": 6,
          "media_count": 5866,
          "tweet_count": 24114
        },
        "url": "https://t.co/b8Rzwcvm1z",
        "username": "A1oneSKy",
        "verified": true
      }
    ]
  }
}