{
  "data": {
    "article": {},
    "attachments": {},
    "author_id": "1839263401845075974",
    "conversation_id": "2050934951395398061",
    "created_at": "2026-05-03T17:23:25.000Z",
    "edit_controls": {
      "editable_until": "2026-05-03T18:23:25.000Z",
      "edits_remaining": 5,
      "is_edit_eligible": false
    },
    "edit_history_tweet_ids": [
      "2050989620213756348"
    ],
    "entities": {
      "mentions": [
        {
          "end": 16,
          "id": "1699273459325390848",
          "start": 0,
          "username": "DurantRaym93677"
        }
      ]
    },
    "geo": {},
    "id": "2050989620213756348",
    "in_reply_to_user_id": "1699273459325390848",
    "lang": "qme",
    "note_tweet": {
      "entities": {}
    },
    "possibly_sensitive": false,
    "public_metrics": {
      "bookmark_count": 0,
      "impression_count": 0,
      "like_count": 1,
      "quote_count": 0,
      "reply_count": 0,
      "retweet_count": 0
    },
    "referenced_tweets": [
      {
        "id": "2050934951395398061",
        "type": "replied_to"
      }
    ],
    "reply_settings": "everyone",
    "text": "@DurantRaym93677 🥺🥺🥺🥺🥺🥺🥺🥺🥺🥺🥺🥺🥺🥺🥺🥺🥺🥺🥺🥺🥺🥺🥺🥺🥺🥺🥺🥺🥺🥺🥺🥺🥺🥺🥺🥺🥺🥺🥺🥺🥺🥺🥺🥺🥺🥺🥺🥺🥺🥺🥺🥺🥺🥺🥺🥺🥺🥺🥺🥺🥺🥺🥺🥺🥺🥺🥺🥺🥺🥺🥺🥺🥺🥺🥺🥺🥺🥺🥺🥺🥺🥺🥺🥺🥺🥺🥺🥺🥺🥺🥺🥺🥺🥺🥺🥺🥺🥺🥺🥺🥺🥺🥺🥺🥺🥺🥺🥺🥺🥺🥺🥺🥺🥺🥺🥺🥺🥺🥺🥺🥺🥺🥺🥺🥺🥺🥺🥺🥺🥺🥺🥺🥺🥺🥺🥺🥺🥺🥺🥺"
  },
  "includes": {
    "media": [
      {
        "height": 1206,
        "media_key": "3_2050934921276055552",
        "public_metrics": {},
        "type": "photo",
        "url": "https://pbs.twimg.com/media/HHZicdAaYAANBfU.jpg",
        "width": 2622
      }
    ],
    "tweets": [
      {
        "article": {},
        "attachments": {},
        "author_id": "1839263401845075974",
        "conversation_id": "2050934951395398061",
        "created_at": "2026-05-03T17:23:25.000Z",
        "edit_controls": {
          "editable_until": "2026-05-03T18:23:25.000Z",
          "edits_remaining": 5,
          "is_edit_eligible": false
        },
        "edit_history_tweet_ids": [
          "2050989620213756348"
        ],
        "entities": {
          "mentions": [
            {
              "end": 16,
              "id": "1699273459325390848",
              "start": 0,
              "username": "DurantRaym93677"
            }
          ]
        },
        "geo": {},
        "id": "2050989620213756348",
        "in_reply_to_user_id": "1699273459325390848",
        "lang": "qme",
        "note_tweet": {
          "entities": {}
        },
        "possibly_sensitive": false,
        "public_metrics": {
          "bookmark_count": 0,
          "impression_count": 0,
          "like_count": 1,
          "quote_count": 0,
          "reply_count": 0,
          "retweet_count": 0
        },
        "referenced_tweets": [
          {
            "id": "2050934951395398061",
            "type": "replied_to"
          }
        ],
        "reply_settings": "everyone",
        "text": "@DurantRaym93677 🥺🥺🥺🥺🥺🥺🥺🥺🥺🥺🥺🥺🥺🥺🥺🥺🥺🥺🥺🥺🥺🥺🥺🥺🥺🥺🥺🥺🥺🥺🥺🥺🥺🥺🥺🥺🥺🥺🥺🥺🥺🥺🥺🥺🥺🥺🥺🥺🥺🥺🥺🥺🥺🥺🥺🥺🥺🥺🥺🥺🥺🥺🥺🥺🥺🥺🥺🥺🥺🥺🥺🥺🥺🥺🥺🥺🥺🥺🥺🥺🥺🥺🥺🥺🥺🥺🥺🥺🥺🥺🥺🥺🥺🥺🥺🥺🥺🥺🥺🥺🥺🥺🥺🥺🥺🥺🥺🥺🥺🥺🥺🥺🥺🥺🥺🥺🥺🥺🥺🥺🥺🥺🥺🥺🥺🥺🥺🥺🥺🥺🥺🥺🥺🥺🥺🥺🥺🥺🥺🥺"
      },
      {
        "article": {},
        "attachments": {
          "media_keys": [
            "3_2050934921276055552"
          ]
        },
        "author_id": "1699273459325390848",
        "context_annotations": [
          {
            "domain": {
              "description": "Categories within Brand Verticals that narrow down the scope of Brands",
              "id": "46",
              "name": "Business Taxonomy"
            },
            "entity": {
              "description": "Brands, companies, advertisers and every non-person handle with the profit intent related to offline and online games such as gaming consoles, tabletop games, video game publishers",
              "id": "1557696940178935808",
              "name": "Gaming Business"
            }
          },
          {
            "domain": {
              "description": "A video game like Overwatch",
              "id": "71",
              "name": "Video Game"
            },
            "entity": {
              "id": "1370105546607534081",
              "name": "Project Sekai"
            }
          },
          {
            "domain": {
              "description": "A taxonomy of user interests. ",
              "id": "131",
              "name": "Unified Twitter Taxonomy"
            },
            "entity": {
              "id": "1370105546607534081",
              "name": "Project Sekai"
            }
          }
        ],
        "conversation_id": "2050934951395398061",
        "created_at": "2026-05-03T13:46:11.000Z",
        "edit_controls": {
          "editable_until": "2026-05-03T14:46:11.000Z",
          "edits_remaining": 5,
          "is_edit_eligible": true
        },
        "edit_history_tweet_ids": [
          "2050934951395398061"
        ],
        "entities": {
          "urls": [
            {
              "display_url": "pic.x.com/hc1THKe1xZ",
              "end": 41,
              "expanded_url": "https://x.com/DurantRaym93677/status/2050934951395398061/photo/1",
              "media_key": "3_2050934921276055552",
              "start": 18,
              "url": "https://t.co/hc1THKe1xZ"
            }
          ]
        },
        "geo": {},
        "id": "2050934951395398061",
        "lang": "ja",
        "note_tweet": {
          "entities": {}
        },
        "possibly_sensitive": false,
        "public_metrics": {
          "bookmark_count": 0,
          "impression_count": 147,
          "like_count": 8,
          "quote_count": 0,
          "reply_count": 0,
          "retweet_count": 0
        },
        "reply_settings": "everyone",
        "text": "プロセカ还是得插有线耳机玩才舒服😇 https://t.co/hc1THKe1xZ"
      }
    ],
    "users": [
      {
        "created_at": "2024-09-26T11:19:31.000Z",
        "description": "私たちは二次元をこれほど熱愛している \n\n🇦🇶🇦🇶🇦🇶",
        "id": "1839263401845075974",
        "location": "Neoaurorium City",
        "name": "mortis",
        "pinned_tweet_id": "1895931291142627425",
        "profile_image_url": "https://pbs.twimg.com/profile_images/1971955303194546176/7EbSCYUF_normal.jpg",
        "protected": false,
        "public_metrics": {
          "followers_count": 1957,
          "following_count": 2749,
          "like_count": 29970,
          "listed_count": 10,
          "media_count": 335,
          "tweet_count": 10346
        },
        "username": "0Yowlry",
        "verified": false
      },
      {
        "created_at": "2023-09-06T04:09:04.000Z",
        "description": "🍊 あぁ 闇はただ純粋で | \n🚼 🔑サブ: @AmmieColl84391 (フォロー歓迎) | 💼 Speaker of the Parliament of @enchenia | 💕 @chiyorin8964",
        "entities": {
          "description": {
            "mentions": [
              {
                "end": 38,
                "start": 23,
                "username": "AmmieColl84391"
              },
              {
                "end": 90,
                "start": 81,
                "username": "enchenia"
              },
              {
                "end": 108,
                "start": 95,
                "username": "chiyorin8964"
              }
            ]
          }
        },
        "id": "1699273459325390848",
        "location": "Japan",
        "name": "Luke 鈴木 サクラみ🥦⛩️",
        "profile_image_url": "https://pbs.twimg.com/profile_images/2036740912668389376/LWPePSYk_normal.png",
        "protected": false,
        "public_metrics": {
          "followers_count": 2972,
          "following_count": 3147,
          "like_count": 45677,
          "listed_count": 16,
          "media_count": 533,
          "tweet_count": 11094
        },
        "username": "DurantRaym93677",
        "verified": true
      }
    ]
  }
}