{
  "data": {
    "article": {},
    "attachments": {},
    "author_id": "1839263401845075974",
    "conversation_id": "2064629695740522707",
    "created_at": "2026-06-10T11:20:05.000Z",
    "edit_controls": {
      "editable_until": "2026-06-10T12:20:05.000Z",
      "edits_remaining": 5,
      "is_edit_eligible": false
    },
    "edit_history_tweet_ids": [
      "2064668920666370408"
    ],
    "entities": {
      "mentions": [
        {
          "end": 11,
          "id": "1108737084301307904",
          "start": 0,
          "username": "EntropyF73"
        }
      ]
    },
    "geo": {},
    "id": "2064668920666370408",
    "in_reply_to_user_id": "1108737084301307904",
    "lang": "zh",
    "note_tweet": {
      "entities": {}
    },
    "possibly_sensitive": false,
    "public_metrics": {
      "bookmark_count": 0,
      "impression_count": 0,
      "like_count": 1,
      "quote_count": 0,
      "reply_count": 0,
      "retweet_count": 0
    },
    "referenced_tweets": [
      {
        "id": "2064629695740522707",
        "type": "replied_to"
      }
    ],
    "reply_settings": "everyone",
    "text": "@EntropyF73 大马和星加坡和土耳其和马尔代夫应该是为数不多免签还值得去的了吧"
  },
  "includes": {
    "tweets": [
      {
        "article": {},
        "attachments": {},
        "author_id": "1839263401845075974",
        "conversation_id": "2064629695740522707",
        "created_at": "2026-06-10T11:20:05.000Z",
        "edit_controls": {
          "editable_until": "2026-06-10T12:20:05.000Z",
          "edits_remaining": 5,
          "is_edit_eligible": false
        },
        "edit_history_tweet_ids": [
          "2064668920666370408"
        ],
        "entities": {
          "mentions": [
            {
              "end": 11,
              "id": "1108737084301307904",
              "start": 0,
              "username": "EntropyF73"
            }
          ]
        },
        "geo": {},
        "id": "2064668920666370408",
        "in_reply_to_user_id": "1108737084301307904",
        "lang": "zh",
        "note_tweet": {
          "entities": {}
        },
        "possibly_sensitive": false,
        "public_metrics": {
          "bookmark_count": 0,
          "impression_count": 0,
          "like_count": 1,
          "quote_count": 0,
          "reply_count": 0,
          "retweet_count": 0
        },
        "referenced_tweets": [
          {
            "id": "2064629695740522707",
            "type": "replied_to"
          }
        ],
        "reply_settings": "everyone",
        "text": "@EntropyF73 大马和星加坡和土耳其和马尔代夫应该是为数不多免签还值得去的了吧"
      },
      {
        "article": {},
        "attachments": {},
        "author_id": "1108737084301307904",
        "conversation_id": "2064629695740522707",
        "created_at": "2026-06-10T08:44:13.000Z",
        "edit_controls": {
          "editable_until": "2026-06-10T09:44:13.000Z",
          "edits_remaining": 5,
          "is_edit_eligible": true
        },
        "edit_history_tweet_ids": [
          "2064629695740522707"
        ],
        "entities": {},
        "geo": {},
        "id": "2064629695740522707",
        "lang": "zh",
        "note_tweet": {
          "entities": {}
        },
        "possibly_sensitive": false,
        "public_metrics": {
          "bookmark_count": 0,
          "impression_count": 303,
          "like_count": 10,
          "quote_count": 0,
          "reply_count": 4,
          "retweet_count": 0
        },
        "reply_settings": "everyone",
        "text": "大概率我的gap一年不会到处旅游，办签证这一步就能把我累到，如果到时候能规律直播就算很厉害了，尽量不退网吧，比较多时间估计窝着看剧补番，哦对，还要赚钱"
      }
    ],
    "users": [
      {
        "created_at": "2024-09-26T11:19:31.000Z",
        "description": "私たちは二次元をこれほど熱愛している \n\n🇦🇶🇦🇶🇦🇶",
        "id": "1839263401845075974",
        "location": "Neoaurorium City",
        "name": "mortis",
        "pinned_tweet_id": "1895931291142627425",
        "profile_image_url": "https://pbs.twimg.com/profile_images/1971955303194546176/7EbSCYUF_normal.jpg",
        "protected": false,
        "public_metrics": {
          "followers_count": 2083,
          "following_count": 2986,
          "like_count": 37885,
          "listed_count": 10,
          "media_count": 367,
          "tweet_count": 12234
        },
        "username": "0Yowlry",
        "verified": false
      },
      {
        "created_at": "2019-03-21T14:28:15.000Z",
        "description": "🏳️‍🌈+🖤🩶🤍💜 Indie VTuber 个人势 | enby INFJ-A 中文 & EN｜Weibo & Bilibili: 熵x殇Entropy (GB based) cptsd自救 | Support Me⬇️",
        "entities": {
          "url": {
            "urls": [
              {
                "display_url": "buymeacoffee.com/entropyf73",
                "end": 23,
                "expanded_url": "http://buymeacoffee.com/entropyf73",
                "start": 0,
                "url": "https://t.co/aSj9f0QHM2"
              }
            ]
          }
        },
        "id": "1108737084301307904",
        "location": "East, England",
        "name": "Entropy 📎💙",
        "pinned_tweet_id": "1548475185132552193",
        "profile_image_url": "https://pbs.twimg.com/profile_images/1546099766416871426/3J0rGG_I_normal.jpg",
        "protected": false,
        "public_metrics": {
          "followers_count": 837,
          "following_count": 1219,
          "like_count": 31579,
          "listed_count": 2,
          "media_count": 324,
          "tweet_count": 3048
        },
        "url": "https://t.co/aSj9f0QHM2",
        "username": "EntropyF73",
        "verified": true
      }
    ]
  }
}